{
    "annotations": {
        "list": [
            {
                "builtIn": 1,
                "datasource": "-- Grafana --",
                "enable": true,
                "hide": true,
                "iconColor": "rgba(0, 211, 255, 1)",
                "name": "Annotations & Alerts",
                "type": "dashboard"
            }
        ]
    },
    "editable": true,
    "gnetId": null,
    "graphTooltip": 0,
    "id": null,
    "links": [],
    "panels": [
        {
            "datasource": {
                "type": "postgres",
                "uid": "postgres-datasource"
            },
            "fieldConfig": {
                "defaults": {
                    "color": {
                        "mode": "thresholds"
                    },
                    "mappings": [],
                    "thresholds": {
                        "mode": "absolute",
                        "steps": [
                            {
                                "color": "green",
                                "value": null
                            },
                            {
                                "color": "red",
                                "value": 80
                            }
                        ]
                    }
                },
                "overrides": []
            },
            "gridPos": {
                "h": 8,
                "w": 12,
                "x": 0,
                "y": 0
            },
            "id": 2,
            "options": {
                "colorMode": "value",
                "graphMode": "area",
                "justifyMode": "auto",
                "orientation": "auto",
                "reduceOptions": {
                    "calcs": [
                        "lastNotNull"
                    ],
                    "fields": "",
                    "values": false
                },
                "textMode": "auto"
            },
            "pluginVersion": "8.3.3",
            "targets": [
                {
                    "format": "table",
                    "group": [],
                    "metricColumn": "none",
                    "rawQuery": true,
                    "rawSql": "SELECT count(*) as product_count FROM products",
                    "refId": "A",
                    "select": [
                        [
                            {
                                "params": [
                                    "value"
                                ],
                                "type": "column"
                            }
                        ]
                    ],
                    "table": "products",
                    "timeColumn": "time",
                    "timeColumnType": "timestamp",
                    "where": []
                }
            ],
            "title": "Total Products",
            "type": "stat"
        },
        {
            "datasource": {
                "type": "postgres",
                "uid": "postgres-datasource"
            },
            "fieldConfig": {
                "defaults": {
                    "color": {
                        "mode": "thresholds"
                    },
                    "custom": {
                        "align": "auto",
                        "displayMode": "auto"
                    },
                    "mappings": [],
                    "thresholds": {
                        "mode": "absolute",
                        "steps": [
                            {
                                "color": "green",
                                "value": null
                            },
                            {
                                "color": "red",
                                "value": 80
                            }
                        ]
                    }
                },
                "overrides": []
            },
            "gridPos": {
                "h": 8,
                "w": 12,
                "x": 12,
                "y": 0
            },
            "id": 3,
            "options": {
                "footer": {
                    "fields": "",
                    "reducer": [
                        "sum"
                    ],
                    "show": false
                },
                "showHeader": true
            },
            "pluginVersion": "8.3.3",
            "targets": [
                {
                    "format": "table",
                    "group": [],
                    "metricColumn": "none",
                    "rawQuery": true,
                    "rawSql": "SELECT * FROM products LIMIT 10",
                    "refId": "A",
                    "select": [
                        [
                            {
                                "params": [
                                    "value"
                                ],
                                "type": "column"
                            }
                        ]
                    ],
                    "table": "products",
                    "timeColumn": "time",
                    "timeColumnType": "timestamp",
                    "where": []
                }
            ],
            "title": "Recent Products",
            "type": "table"
        }
    ],
    "refresh": "5s",
    "schemaVersion": 34,
    "style": "dark",
    "tags": [],
    "templating": {
        "list": []
    },
    "time": {
        "from": "now-6h",
        "to": "now"
    },
    "timepicker": {},
    "timezone": "",
    "title": "Product Database Stats",
    "uid": "postgres-stats",
    "version": 1,
    "weekStart": ""
}